djp_py_helpers/__init__.py
djp_py_helpers/logging.py
djp_py_helpers-1.0.0.dist-info/LICENSE
djp_py_helpers-1.0.0.dist-info/METADATA
djp_py_helpers-1.0.0.dist-info/WHEEL
djp_py_helpers-1.0.0.dist-info/RECORD
