Metadata-Version: 2.1
Name: djp-py-helpers
Version: 1.0.0
Summary: python helper functions
License: MIT
Author: Dawson Pleasant
Author-email: dawsonpleasant@outlook.com
Requires-Python: >=3.11,<4.0
Classifier: License :: OSI Approved :: MIT License
Classifier: Programming Language :: Python :: 3
Classifier: Programming Language :: Python :: 3.11
